[
    {
        "player_id": 102383,
        "stats": {
            "MIN": 29,
            "GL": 0,
            "ASS": 0,
            "CS": 1,
            "SV": 0,
            "PE": 1,
            "PS": 0,
            "PM": 0,
            "GC": 0,
            "YC": 0,
            "RC": 0,
            "OG": 0,
            "OGA": 0,
            "SH": 0,
            "WF": 2,
            "PSS": 11,
            "APS": 7,
            "CRS": 0,
            "KP": 0,
            "BC": 0,
            "CL": 1,
            "BLK": 0,
            "INT": 0,
            "TCK": 1,
            "BR": 0,
            "ELG": 0
        }
    },
    {
        "player_id": 110974,
        "stats": {
            "MIN": 61,
            "GL": 0,
            "ASS": 0,
            "CS": 0,
            "SV": 0,
            "PE": 0,
            "PS": 0,
            "PM": 0,
            "GC": 1,
            "YC": 0,
            "RC": 0,
            "OG": 0,
            "OGA": 0,
            "SH": 0,
            "WF": 0,
            "PSS": 17,
            "APS": 11,
            "CRS": 0,
            "KP": 0,
            "BC": 0,
            "CL": 1,
            "BLK": 0,
            "INT": 0,
            "TCK": 1,
            "BR": 4,
            "ELG": 0
        }
    },
    {
        "player_id": 132113,
        "stats": {
            "MIN": 90,
            "GL": 0,
            "ASS": 0,
            "CS": 0,
            "SV": 0,
            "PE": 0,
            "PS": 0,
            "PM": 0,
            "GC": 1,
            "YC": 0,
            "RC": 0,
            "OG": 0,
            "OGA": 0,
            "SH": 0,
            "WF": 1,
            "PSS": 38,
            "APS": 28,
            "CRS": 0,
            "KP": 0,
            "BC": 0,
            "CL": 5,
            "BLK": 0,
            "INT": 2,
            "TCK": 1,
            "BR": 3,
            "ELG": 0
        }
    },
    {
        "player_id": 149231,
        "stats": {
            "MIN": 45,
            "GL": 0,
            "ASS": 0,
            "CS": 1,
            "SV": 0,
            "PE": 0,
            "PS": 0,
            "PM": 0,
            "GC": 0,
            "YC": 0,
            "RC": 0,
            "OG": 0,
            "OGA": 0,
            "SH": 0,
            "WF": 0,
            "PSS": 23,
            "APS": 18,
            "CRS": 1,
            "KP": 2,
            "BC": 0,
            "CL": 0,
            "BLK": 0,
            "INT": 0,
            "TCK": 3,
            "BR": 5,
            "ELG": 0
        }
    },
    {
        "player_id": 153264,
        "stats": {
            "MIN": 90,
            "GL": 0,
            "ASS": 0,
            "CS": 0,
            "SV": 0,
            "PE": 0,
            "PS": 0,
            "PM": 0,
            "GC": 1,
            "YC": 0,
            "RC": 0,
            "OG": 0,
            "OGA": 0,
            "SH": 0,
            "WF": 0,
            "PSS": 46,
            "APS": 30,
            "CRS": 0,
            "KP": 1,
            "BC": 0,
            "CL": 5,
            "BLK": 0,
            "INT": 0,
            "TCK": 2,
            "BR": 8,
            "ELG": 0
        }
    },
    {
        "player_id": 179384,
        "stats": {
            "MIN": 90,
            "GL": 1,
            "ASS": 0,
            "CS": 0,
            "SV": 0,
            "PE": 0,
            "PS": 0,
            "PM": 0,
            "GC": 1,
            "YC": 0,
            "RC": 0,
            "OG": 0,
            "OGA": 0,
            "SH": 3,
            "WF": 1,
            "PSS": 36,
            "APS": 29,
            "CRS": 1,
            "KP": 1,
            "BC": 0,
            "CL": 0,
            "BLK": 0,
            "INT": 1,
            "TCK": 1,
            "BR": 8,
            "ELG": 0
        }
    },
    {
        "player_id": 179527,
        "stats": {
            "MIN": 90,
            "GL": 0,
            "ASS": 0,
            "CS": 0,
            "SV": 0,
            "PE": 0,
            "PS": 0,
            "PM": 0,
            "GC": 2,
            "YC": 1,
            "RC": 0,
            "OG": 0,
            "OGA": 0,
            "SH": 2,
            "WF": 1,
            "PSS": 19,
            "APS": 15,
            "CRS": 0,
            "KP": 0,
            "BC": 0,
            "CL": 1,
            "BLK": 0,
            "INT": 0,
            "TCK": 3,
            "BR": 3,
            "ELG": 0
        }
    },
    {
        "player_id": 201125,
        "stats": {
            "MIN": 29,
            "GL": 0,
            "ASS": 0,
            "CS": 1,
            "SV": 0,
            "PE": 0,
            "PS": 0,
            "PM": 0,
            "GC": 0,
            "YC": 1,
            "RC": 0,
            "OG": 0,
            "OGA": 0,
            "SH": 0,
            "WF": 0,
            "PSS": 8,
            "APS": 5,
            "CRS": 0,
            "KP": 0,
            "BC": 0,
            "CL": 1,
            "BLK": 0,
            "INT": 0,
            "TCK": 0,
            "BR": 3,
            "ELG": 0
        }
    },
    {
        "player_id": 201558,
        "stats": {
            "MIN": 90,
            "GL": 0,
            "ASS": 0,
            "CS": 0,
            "SV": 1,
            "PE": 0,
            "PS": 0,
            "PM": 0,
            "GC": 2,
            "YC": 0,
            "RC": 0,
            "OG": 0,
            "OGA": 0,
            "SH": 0,
            "WF": 0,
            "PSS": 24,
            "APS": 7,
            "CRS": 0,
            "KP": 0,
            "BC": 0,
            "CL": 2,
            "BLK": 0,
            "INT": 0,
            "TCK": 0,
            "BR": 5,
            "ELG": 1
        }
    },
    {
        "player_id": 204254,
        "stats": {
            "MIN": 90,
            "GL": 1,
            "ASS": 0,
            "CS": 0,
            "SV": 0,
            "PE": 0,
            "PS": 0,
            "PM": 0,
            "GC": 2,
            "YC": 0,
            "RC": 0,
            "OG": 0,
            "OGA": 0,
            "SH": 1,
            "WF": 1,
            "PSS": 22,
            "APS": 17,
            "CRS": 0,
            "KP": 1,
            "BC": 0,
            "CL": 0,
            "BLK": 0,
            "INT": 1,
            "TCK": 2,
            "BR": 5,
            "ELG": 0
        }
    },
    {
        "player_id": 234346,
        "stats": {
            "MIN": 72,
            "GL": 0,
            "ASS": 0,
            "CS": 1,
            "SV": 0,
            "PE": 0,
            "PS": 0,
            "PM": 0,
            "GC": 0,
            "YC": 0,
            "RC": 0,
            "OG": 0,
            "OGA": 0,
            "SH": 1,
            "WF": 0,
            "PSS": 19,
            "APS": 10,
            "CRS": 0,
            "KP": 0,
            "BC": 0,
            "CL": 0,
            "BLK": 0,
            "INT": 0,
            "TCK": 1,
            "BR": 5,
            "ELG": 0
        }
    },
    {
        "player_id": 244899,
        "stats": {
            "MIN": 90,
            "GL": 0,
            "ASS": 0,
            "CS": 0,
            "SV": 0,
            "PE": 0,
            "PS": 0,
            "PM": 0,
            "GC": 2,
            "YC": 0,
            "RC": 0,
            "OG": 0,
            "OGA": 0,
            "SH": 0,
            "WF": 0,
            "PSS": 24,
            "APS": 14,
            "CRS": 0,
            "KP": 0,
            "BC": 0,
            "CL": 3,
            "BLK": 0,
            "INT": 1,
            "TCK": 3,
            "BR": 7,
            "ELG": 0
        }
    },
    {
        "player_id": 247041,
        "stats": {
            "MIN": 80,
            "GL": 0,
            "ASS": 0,
            "CS": 0,
            "SV": 0,
            "PE": 0,
            "PS": 0,
            "PM": 0,
            "GC": 1,
            "YC": 1,
            "RC": 0,
            "OG": 0,
            "OGA": 0,
            "SH": 0,
            "WF": 0,
            "PSS": 21,
            "APS": 10,
            "CRS": 0,
            "KP": 0,
            "BC": 0,
            "CL": 3,
            "BLK": 2,
            "INT": 2,
            "TCK": 5,
            "BR": 6,
            "ELG": 0
        }
    },
    {
        "player_id": 424659,
        "stats": {
            "MIN": 90,
            "GL": 0,
            "ASS": 0,
            "CS": 0,
            "SV": 0,
            "PE": 0,
            "PS": 0,
            "PM": 0,
            "GC": 2,
            "YC": 0,
            "RC": 0,
            "OG": 0,
            "OGA": 0,
            "SH": 1,
            "WF": 2,
            "PSS": 42,
            "APS": 31,
            "CRS": 2,
            "KP": 2,
            "BC": 0,
            "CL": 0,
            "BLK": 0,
            "INT": 0,
            "TCK": 2,
            "BR": 5,
            "ELG": 0
        }
    },
    {
        "player_id": 424761,
        "stats": {
            "MIN": 90,
            "GL": 0,
            "ASS": 0,
            "CS": 0,
            "SV": 0,
            "PE": 0,
            "PS": 0,
            "PM": 0,
            "GC": 1,
            "YC": 0,
            "RC": 0,
            "OG": 0,
            "OGA": 0,
            "SH": 0,
            "WF": 0,
            "PSS": 29,
            "APS": 15,
            "CRS": 0,
            "KP": 0,
            "BC": 0,
            "CL": 1,
            "BLK": 0,
            "INT": 0,
            "TCK": 0,
            "BR": 6,
            "ELG": 0
        }
    },
    {
        "player_id": 426027,
        "stats": {
            "MIN": 26,
            "GL": 0,
            "ASS": 0,
            "CS": 0,
            "SV": 0,
            "PE": 0,
            "PS": 0,
            "PM": 0,
            "GC": 2,
            "YC": 0,
            "RC": 0,
            "OG": 0,
            "OGA": 0,
            "SH": 1,
            "WF": 0,
            "PSS": 6,
            "APS": 4,
            "CRS": 0,
            "KP": 0,
            "BC": 0,
            "CL": 1,
            "BLK": 0,
            "INT": 2,
            "TCK": 2,
            "BR": 4,
            "ELG": 0
        }
    },
    {
        "player_id": 427231,
        "stats": {
            "MIN": 64,
            "GL": 0,
            "ASS": 0,
            "CS": 1,
            "SV": 0,
            "PE": 0,
            "PS": 0,
            "PM": 0,
            "GC": 0,
            "YC": 0,
            "RC": 0,
            "OG": 0,
            "OGA": 0,
            "SH": 1,
            "WF": 1,
            "PSS": 27,
            "APS": 18,
            "CRS": 1,
            "KP": 1,
            "BC": 0,
            "CL": 0,
            "BLK": 0,
            "INT": 2,
            "TCK": 2,
            "BR": 5,
            "ELG": 0
        }
    },
    {
        "player_id": 430076,
        "stats": {
            "MIN": 90,
            "GL": 1,
            "ASS": 0,
            "CS": 0,
            "SV": 0,
            "PE": 0,
            "PS": 0,
            "PM": 0,
            "GC": 1,
            "YC": 0,
            "RC": 0,
            "OG": 0,
            "OGA": 0,
            "SH": 2,
            "WF": 1,
            "PSS": 36,
            "APS": 32,
            "CRS": 0,
            "KP": 0,
            "BC": 0,
            "CL": 1,
            "BLK": 0,
            "INT": 2,
            "TCK": 4,
            "BR": 10,
            "ELG": 0
        }
    },
    {
        "player_id": 432587,
        "stats": {
            "MIN": 10,
            "GL": 0,
            "ASS": 0,
            "CS": 0,
            "SV": 0,
            "PE": 0,
            "PS": 0,
            "PM": 0,
            "GC": 1,
            "YC": 0,
            "RC": 0,
            "OG": 0,
            "OGA": 0,
            "SH": 0,
            "WF": 0,
            "PSS": 6,
            "APS": 5,
            "CRS": 0,
            "KP": 0,
            "BC": 0,
            "CL": 0,
            "BLK": 0,
            "INT": 0,
            "TCK": 1,
            "BR": 0,
            "ELG": 0
        }
    },
    {
        "player_id": 436594,
        "stats": {
            "MIN": 45,
            "GL": 0,
            "ASS": 0,
            "CS": 0,
            "SV": 0,
            "PE": 0,
            "PS": 0,
            "PM": 0,
            "GC": 1,
            "YC": 1,
            "RC": 0,
            "OG": 0,
            "OGA": 0,
            "SH": 0,
            "WF": 1,
            "PSS": 16,
            "APS": 12,
            "CRS": 0,
            "KP": 0,
            "BC": 0,
            "CL": 0,
            "BLK": 0,
            "INT": 0,
            "TCK": 1,
            "BR": 2,
            "ELG": 0
        }
    },
    {
        "player_id": 440726,
        "stats": {
            "MIN": 90,
            "GL": 0,
            "ASS": 0,
            "CS": 0,
            "SV": 0,
            "PE": 0,
            "PS": 0,
            "PM": 0,
            "GC": 2,
            "YC": 0,
            "RC": 0,
            "OG": 0,
            "OGA": 0,
            "SH": 2,
            "WF": 0,
            "PSS": 21,
            "APS": 15,
            "CRS": 0,
            "KP": 0,
            "BC": 0,
            "CL": 0,
            "BLK": 0,
            "INT": 0,
            "TCK": 1,
            "BR": 5,
            "ELG": 0
        }
    },
    {
        "player_id": 448116,
        "stats": {
            "MIN": 61,
            "GL": 0,
            "ASS": 0,
            "CS": 0,
            "SV": 0,
            "PE": 0,
            "PS": 0,
            "PM": 0,
            "GC": 1,
            "YC": 0,
            "RC": 0,
            "OG": 0,
            "OGA": 0,
            "SH": 0,
            "WF": 0,
            "PSS": 13,
            "APS": 9,
            "CRS": 0,
            "KP": 0,
            "BC": 0,
            "CL": 0,
            "BLK": 0,
            "INT": 0,
            "TCK": 1,
            "BR": 3,
            "ELG": 0
        }
    },
    {
        "player_id": 453637,
        "stats": {
            "MIN": 89,
            "GL": 0,
            "ASS": 0,
            "CS": 0,
            "SV": 0,
            "PE": 0,
            "PS": 0,
            "PM": 0,
            "GC": 1,
            "YC": 0,
            "RC": 0,
            "OG": 0,
            "OGA": 0,
            "SH": 0,
            "WF": 0,
            "PSS": 40,
            "APS": 29,
            "CRS": 1,
            "KP": 0,
            "BC": 0,
            "CL": 2,
            "BLK": 0,
            "INT": 0,
            "TCK": 1,
            "BR": 7,
            "ELG": 0
        }
    },
    {
        "player_id": 468444,
        "stats": {
            "MIN": 90,
            "GL": 0,
            "ASS": 0,
            "CS": 0,
            "SV": 0,
            "PE": 0,
            "PS": 0,
            "PM": 0,
            "GC": 2,
            "YC": 1,
            "RC": 0,
            "OG": 0,
            "OGA": 0,
            "SH": 0,
            "WF": 4,
            "PSS": 52,
            "APS": 40,
            "CRS": 0,
            "KP": 2,
            "BC": 0,
            "CL": 0,
            "BLK": 0,
            "INT": 2,
            "TCK": 4,
            "BR": 9,
            "ELG": 0
        }
    },
    {
        "player_id": 471210,
        "stats": {
            "MIN": 73,
            "GL": 0,
            "ASS": 0,
            "CS": 0,
            "SV": 0,
            "PE": 0,
            "PS": 0,
            "PM": 0,
            "GC": 1,
            "YC": 1,
            "RC": 0,
            "OG": 0,
            "OGA": 0,
            "SH": 2,
            "WF": 2,
            "PSS": 14,
            "APS": 13,
            "CRS": 0,
            "KP": 0,
            "BC": 0,
            "CL": 0,
            "BLK": 0,
            "INT": 0,
            "TCK": 1,
            "BR": 2,
            "ELG": 0
        }
    },
    {
        "player_id": 477535,
        "stats": {
            "MIN": 90,
            "GL": 0,
            "ASS": 0,
            "CS": 0,
            "SV": 0,
            "PE": 0,
            "PS": 0,
            "PM": 0,
            "GC": 2,
            "YC": 0,
            "RC": 0,
            "OG": 0,
            "OGA": 0,
            "SH": 0,
            "WF": 0,
            "PSS": 32,
            "APS": 22,
            "CRS": 0,
            "KP": 0,
            "BC": 0,
            "CL": 3,
            "BLK": 0,
            "INT": 1,
            "TCK": 2,
            "BR": 12,
            "ELG": 0
        }
    },
    {
        "player_id": 479771,
        "stats": {
            "MIN": 1,
            "GL": 0,
            "ASS": 0,
            "CS": 1,
            "SV": 0,
            "PE": 0,
            "PS": 0,
            "PM": 0,
            "GC": 0,
            "YC": 0,
            "RC": 0,
            "OG": 0,
            "OGA": 0,
            "SH": 0,
            "WF": 0,
            "PSS": 0,
            "APS": 0,
            "CRS": 0,
            "KP": 0,
            "BC": 0,
            "CL": 0,
            "BLK": 0,
            "INT": 0,
            "TCK": 0,
            "BR": 0,
            "ELG": 0
        }
    },
    {
        "player_id": 479806,
        "stats": {
            "MIN": 18,
            "GL": 0,
            "ASS": 0,
            "CS": 0,
            "SV": 0,
            "PE": 0,
            "PS": 0,
            "PM": 0,
            "GC": 2,
            "YC": 0,
            "RC": 0,
            "OG": 0,
            "OGA": 0,
            "SH": 0,
            "WF": 0,
            "PSS": 5,
            "APS": 3,
            "CRS": 1,
            "KP": 1,
            "BC": 0,
            "CL": 0,
            "BLK": 0,
            "INT": 0,
            "TCK": 0,
            "BR": 1,
            "ELG": 0
        }
    },
    {
        "player_id": 501837,
        "stats": {
            "MIN": 90,
            "GL": 0,
            "ASS": 0,
            "CS": 0,
            "SV": 0,
            "PE": 0,
            "PS": 0,
            "PM": 0,
            "GC": 1,
            "YC": 0,
            "RC": 0,
            "OG": 0,
            "OGA": 0,
            "SH": 0,
            "WF": 2,
            "PSS": 64,
            "APS": 47,
            "CRS": 0,
            "KP": 0,
            "BC": 0,
            "CL": 2,
            "BLK": 0,
            "INT": 2,
            "TCK": 1,
            "BR": 14,
            "ELG": 0
        }
    },
    {
        "player_id": 614901,
        "stats": {
            "MIN": 17,
            "GL": 0,
            "ASS": 0,
            "CS": 1,
            "SV": 0,
            "PE": 0,
            "PS": 0,
            "PM": 0,
            "GC": 0,
            "YC": 0,
            "RC": 0,
            "OG": 0,
            "OGA": 0,
            "SH": 0,
            "WF": 1,
            "PSS": 4,
            "APS": 4,
            "CRS": 0,
            "KP": 0,
            "BC": 0,
            "CL": 0,
            "BLK": 0,
            "INT": 0,
            "TCK": 0,
            "BR": 2,
            "ELG": 0
        }
    }
]